django_signals/__init__.py
django_signals/django-signals.py
django_signals-1.0.dist-info/METADATA
django_signals-1.0.dist-info/WHEEL
django_signals-1.0.dist-info/licenses/LICENSE.txt
django_signals-1.0.dist-info/RECORD
